turing_api/__init__.py
turing_api/lib/__init__.py
turing_api/lib/turingAPIException.py
turing_api/lib/visualAPI.py
turing_api/test/__init__.py
turing_api/test/visualAPITest.py
turing_api-1.0.1.dist-info/METADATA
turing_api-1.0.1.dist-info/RECORD
turing_api-1.0.1.dist-info/WHEEL
turing_api-1.0.1.dist-info/top_level.txt
