Metadata-Version: 2.1
Name: turing-api
Version: 1.0.1
Summary: Turing visual search and visually similar recommendations API library for Python
Home-page: https://github.com/turingiq/turing-python
Author: Turing Analytics
Author-email: aditya@turingiq.com
License: UNKNOWN
Platform: UNKNOWN
Classifier: Programming Language :: Python :: 3
Classifier: License :: OSI Approved :: Apache Software License
Classifier: Operating System :: OS Independent
Requires-Dist: requests (==2.*)
